tests/test_basic.py
tests/test_block_allocator.py
tests/test_bumping.py
tests/test_logprobs.py
tests/test_scheduler.py
tests/test_topk.py
tokasaurus/__init__.py
tokasaurus/common_types.py
tokasaurus/core.py
tokasaurus/entry.py
tokasaurus/utils.py
tokasaurus/benchmarks/bench_model.py
tokasaurus/benchmarks/bench_summarization.py
tokasaurus/benchmarks/monkeys_chat.py
tokasaurus/benchmarks/monkeys_gsm8k.py
tokasaurus/benchmarks/monkeys_math500.py
tokasaurus/benchmarks/sharegpt.py
tokasaurus/benchmarks/standalone_monkeys_gsm8k.py
tokasaurus/benchmarks/utils.py
tokasaurus/manager/__init__.py
tokasaurus/manager/allocator.py
tokasaurus/manager/hydragen.py
tokasaurus/manager/input_building.py
tokasaurus/manager/manager.py
tokasaurus/manager/monitoring.py
tokasaurus/manager/scheduler.py
tokasaurus/manager/stopping_predictor.py
tokasaurus/manager/types.py
tokasaurus/model/attention_utils.py
tokasaurus/model/basic_worker.py
tokasaurus/model/entry.py
tokasaurus/model/kv_cache.py
tokasaurus/model/llama.py
tokasaurus/model/pipeline_worker.py
tokasaurus/model/qwen.py
tokasaurus/model/qwen3.py
tokasaurus/model/safetensors_utils.py
tokasaurus/model/types.py
tokasaurus/model/utils.py
tokasaurus/scripts/download.py
tokasaurus/scripts/ping.py
tokasaurus/server/__init__.py
tokasaurus/server/endpoints.py
tokasaurus/server/types.py
tokasaurus/server/utils.py
tokasaurus-0.0.4.dist-info/licenses/LICENSE
tokasaurus-0.0.4.dist-info/METADATA
tokasaurus-0.0.4.dist-info/WHEEL
tokasaurus-0.0.4.dist-info/entry_points.txt
tokasaurus-0.0.4.dist-info/top_level.txt
tokasaurus-0.0.4.dist-info/RECORD
