Metadata-Version: 2.4
Name: tokasaurus
Version: 0.0.4
Summary: The little (LLM) engine that could!
License: 
Classifier: Development Status :: 3 - Alpha
Classifier: Intended Audience :: Developers
Classifier: Programming Language :: Python :: 3
Classifier: License :: OSI Approved :: Apache Software License
Requires-Python: >=3.10
License-File: LICENSE
Requires-Dist: transformers==4.53.0
Requires-Dist: pydra-config>=0.0.13
Requires-Dist: accelerate
Requires-Dist: art
Requires-Dist: statsd
Requires-Dist: fastapi
Requires-Dist: ninja
Requires-Dist: tabulate
Requires-Dist: uvicorn
Requires-Dist: typer
Requires-Dist: openai
Requires-Dist: loguru
Requires-Dist: python-multipart
Requires-Dist: torch==2.6.0
Requires-Dist: flashinfer-python==0.2.0.post2
Requires-Dist: tqdm
Provides-Extra: dev
Requires-Dist: pytest; extra == "dev"
Requires-Dist: datasets; extra == "dev"
Requires-Dist: pyright; extra == "dev"
Requires-Dist: math-verify[antlr4_13_2]; extra == "dev"
Requires-Dist: matplotlib; extra == "dev"
Dynamic: license-file
